groupdocs/signature/py.typed
aspose/pycore/py.typed
aspose/pycore/__init__.pyi
aspose/pyreflection/py.typed
aspose/pyreflection/__init__.pyi
aspose/pydrawing/py.typed
aspose/pydrawing/__init__.pyi
aspose/pydrawing/design.pyi
aspose/pydrawing/drawing2d.pyi
aspose/pydrawing/imaging.pyi
aspose/pydrawing/printing.pyi
aspose/pydrawing/text.pyi
groupdocs/signature/__init__.pyi
groupdocs/signature/domain/__init__.pyi
groupdocs/signature/domain/extensions/__init__.pyi
groupdocs/signature/logging/__init__.pyi
groupdocs/signature/options/__init__.pyi
groupdocs/signature/options/appearances/__init__.pyi
groupdocs/__init__.py
groupdocs/pycore.cpython-310-darwin.so
groupdocs/pycore.cpython-311-darwin.so
groupdocs/pycore.cpython-312-darwin.so
groupdocs/pycore.cpython-313-darwin.so
groupdocs/pycore.cpython-35m-darwin.so
groupdocs/pycore.cpython-36m-darwin.so
groupdocs/pycore.cpython-37m-darwin.so
groupdocs/pycore.cpython-38-darwin.so
groupdocs/pycore.cpython-39-darwin.so
groupdocs/pydrawing.cpython-310-darwin.so
groupdocs/pydrawing.cpython-311-darwin.so
groupdocs/pydrawing.cpython-312-darwin.so
groupdocs/pydrawing.cpython-313-darwin.so
groupdocs/pydrawing.cpython-35m-darwin.so
groupdocs/pydrawing.cpython-36m-darwin.so
groupdocs/pydrawing.cpython-37m-darwin.so
groupdocs/pydrawing.cpython-38-darwin.so
groupdocs/pydrawing.cpython-39-darwin.so
groupdocs/pygc.cpython-310-darwin.so
groupdocs/pygc.cpython-311-darwin.so
groupdocs/pygc.cpython-312-darwin.so
groupdocs/pygc.cpython-313-darwin.so
groupdocs/pygc.cpython-35m-darwin.so
groupdocs/pygc.cpython-36m-darwin.so
groupdocs/pygc.cpython-37m-darwin.so
groupdocs/pygc.cpython-38-darwin.so
groupdocs/pygc.cpython-39-darwin.so
groupdocs/pyreflection.cpython-310-darwin.so
groupdocs/pyreflection.cpython-311-darwin.so
groupdocs/pyreflection.cpython-312-darwin.so
groupdocs/pyreflection.cpython-313-darwin.so
groupdocs/pyreflection.cpython-35m-darwin.so
groupdocs/pyreflection.cpython-36m-darwin.so
groupdocs/pyreflection.cpython-37m-darwin.so
groupdocs_signature_net-25.4.dist-info/METADATA
groupdocs_signature_net-25.4.dist-info/WHEEL
groupdocs_signature_net-25.4.dist-info/entry_points.txt
groupdocs_signature_net-25.4.dist-info/top_level.txt
groupdocs_signature_net-25.4.dist-info/RECORD
