Metadata-Version: 2.1
Name: groupdocs-signature-net
Version: 25.4
Summary: GroupDocs.Signature for Python via .NET is a robust on-premise library designed for adding electronic signatures to documents. This powerful API allows developers to easily integrate digital signatures into their applications without the need for any third-party tools. It supports multiple signature types, such as text, image, barcode, and QR code, providing flexibility across different file formats like PDF, Word, Excel, and more.
Home-page: https://products.groupdocs.com/Signature
Author: GroupDocs
License: Other/Proprietary License
Keywords: Signature,meta,file,render,api,pdf,docx,xlsx,pptx,html,png,word,excel,powerpoint,visio,opendocument,photoshop
Platform: macos_x86_64
Classifier: Operating System :: Microsoft :: Windows
Classifier: Operating System :: POSIX :: Linux
Classifier: Operating System :: Unix
Classifier: License :: Other/Proprietary License
Classifier: Programming Language :: Python :: 3
Classifier: Programming Language :: Python :: 3 :: Only
Classifier: Programming Language :: Python :: 3.8
Classifier: Programming Language :: Python :: 3.9
Classifier: Topic :: Software Development :: Libraries
Classifier: Topic :: Utilities
Requires-Python: >=3.5,<3.14
